{
  "files": [
    {
      "content": "'use client';\n\nimport React from 'react';\n\nimport { BasicElementsPlugin } from '@udecode/plate-basic-elements/react';\nimport { BasicMarksPlugin } from '@udecode/plate-basic-marks/react';\nimport { Plate, usePlateEditor } from '@udecode/plate-common/react';\nimport { ImagePlugin } from '@udecode/plate-media/react';\n\nimport { PlateUI } from '@/plate/demo/plate-ui';\nimport { basicElementsValue } from '@/plate/demo/values/basicElementsValue';\nimport { basicMarksValue } from '@/plate/demo/values/basicMarksValue';\nimport { imageValue } from '@/plate/demo/values/mediaValue';\nimport { deletePlugins } from '@/components/editor/plugins/delete-plugins';\nimport { Editor, EditorContainer } from '@/components/plate-ui/editor';\nimport { FixedToolbar } from '@/components/plate-ui/fixed-toolbar';\nimport { Separator } from '@/components/plate-ui/separator';\nimport { TurnIntoDropdownMenu } from '@/components/plate-ui/turn-into-dropdown-menu';\n\nexport default function MultipleEditorsDemo() {\n  const editor = usePlateEditor({\n    override: { components: PlateUI },\n    plugins: [BasicElementsPlugin, BasicMarksPlugin],\n    value: basicElementsValue,\n  });\n\n  const editorMarks = usePlateEditor({\n    id: 'marks',\n    override: { components: PlateUI },\n    plugins: [BasicElementsPlugin, BasicMarksPlugin],\n    value: basicMarksValue,\n  });\n\n  const editorImage = usePlateEditor({\n    id: 'marks',\n    override: { components: PlateUI },\n    plugins: [\n      BasicElementsPlugin,\n      BasicMarksPlugin,\n      ImagePlugin,\n      ...deletePlugins,\n    ],\n    value: imageValue,\n  });\n\n  return (\n    <Plate editor={editor}>\n      <Plate editor={editorMarks}>\n        <Plate editor={editorImage}>\n          <FixedToolbar>\n            <TurnIntoDropdownMenu />\n          </FixedToolbar>\n\n          <div>\n            <EditorContainer>\n              <Editor />\n            </EditorContainer>\n            <Separator />\n            <EditorContainer>\n              <Editor id=\"marks\" />\n            </EditorContainer>\n            <Separator />\n            <EditorContainer>\n              <Editor id=\"image\" />\n            </EditorContainer>\n          </div>\n        </Plate>\n      </Plate>\n    </Plate>\n  );\n}\n",
      "path": "example/multiple-editors-demo.tsx",
      "target": "components/multiple-editors-demo.tsx",
      "type": "registry:example"
    }
  ],
  "name": "multiple-editors-demo",
  "registryDependencies": [],
  "type": "registry:example"
}