{
  "$schema": "https://ui.shadcn.com/schema/registry-item.json",
  "name": "plate-ui",
  "type": "registry:style",
  "dependencies": [
    "tailwind-scrollbar-hide"
  ],
  "devDependencies": [],
  "registryDependencies": [
    "https://platejs.org/r/plate"
  ],
  "files": [],
  "tailwind": {
    "config": {
      "plugins": [
        "tailwind-scrollbar-hide"
      ]
    }
  },
  "cssVars": {
    "theme": {
      "font-heading": "'var(--font-heading)', 'ui-sans-serif', '-apple-system', 'BlinkMacSystemFont', 'Segoe UI Variable Display', 'Segoe UI', 'Helvetica', 'Apple Color Emoji', 'Arial', 'sans-serif', 'Segoe UI Emoji', 'Segoe UI Symbol', 'Noto Color Emoji'",
      "font-mono": "'var(--font-mono)', ui-monospace, SFMono-Regular, Menlo, Monaco, Consolas, 'Liberation Mono', 'Courier New', monospace",
      "font-sans": "'var(--font-sans)', 'ui-sans-serif', '-apple-system', 'BlinkMacSystemFont', 'Segoe UI Variable Display', 'Segoe UI', 'Helvetica', 'Apple Color Emoji', 'Arial', 'sans-serif', 'Segoe UI Emoji', 'Segoe UI Symbol', 'Noto Color Emoji'"
    },
    "light": {
      "brand": "oklch(0.623 0.214 259.815)",
      "highlight": "oklch(0.852 0.199 91.936)"
    },
    "dark": {
      "brand": "oklch(0.707 0.165 254.624)",
      "highlight": "oklch(0.852 0.199 91.936)"
    }
  }
}